{
  "station": "NIIGATAWMO Station ID:47604",
  "view": "Monthly total of precipitation",
  "data": {
    "Jan": {
      "1881": "\u3000",
      "1882": "111.0",
      "1883": "123.8",
      "1884": "201.3",
      "1885": "117.1",
      "1886": "158.9",
      "1887": "125.9",
      "1888": "150.0",
      "1889": "205.2",
      "1890": "207.3",
      "1891": "372.4",
      "1892": "282.6",
      "1893": "215.3",
      "1894": "151.4",
      "1895": "365.9",
      "1896": "185.9",
      "1897": "147.9",
      "1898": "120.1",
      "1899": "209.4",
      "1900": "206.5",
      "1901": "147.6",
      "1902": "193.3",
      "1903": "171.4",
      "1904": "253.9",
      "1905": "135.0",
      "1906": "173.1",
      "1907": "185.7",
      "1908": "250.9",
      "1909": "147.4",
      "1910": "144.4",
      "1911": "188.1",
      "1912": "192.2",
      "1913": "173.0",
      "1914": "149.8",
      "1915": "175.9",
      "1916": "169.9",
      "1917": "337.2",
      "1918": "149.0",
      "1919": "115.6",
      "1920": "172.4",
      "1921": "210.0",
      "1922": "118.9",
      "1923": "220.0",
      "1924": "228.3",
      "1925": "186.7",
      "1926": "262.4",
      "1927": "126.1",
      "1928": "137.4",
      "1929": "121.0",
      "1930": "161.2",
      "1931": "153.8",
      "1932": "127.5",
      "1933": "235.9",
      "1934": "181.6",
      "1935": "157.1",
      "1936": "199.0",
      "1937": "211.6",
      "1938": "197.8",
      "1939": "229.5",
      "1940": "268.7",
      "1941": "273.1",
      "1942": "261.2",
      "1943": "258.1",
      "1944": "86.3",
      "1945": "255.0",
      "1946": "109.2",
      "1947": "200.2",
      "1948": "138.2",
      "1949": "174.4",
      "1950": "190.7",
      "1951": "143.1",
      "1952": "241.3",
      "1953": "169.0",
      "1954": "142.3",
      "1955": "251.5",
      "1956": "216.2",
      "1957": "120.6",
      "1958": "176.6",
      "1959": "264.5",
      "1960": "207.9",
      "1961": "305.6",
      "1962": "249.5",
      "1963": "359.7",
      "1964": "125.2",
      "1965": "249.4",
      "1966": "105.6",
      "1967": "194.6",
      "1968": "218.5",
      "1969": "296.0",
      "1970": "188.5",
      "1971": "148.0",
      "1972": "130.5",
      "1973": "158.5",
      "1974": "144.5",
      "1975": "165.5",
      "1976": "193.5",
      "1977": "151.5",
      "1978": "205.5",
      "1979": "151.5",
      "1980": "225.0",
      "1981": "132.5",
      "1982": "160.0",
      "1983": "184.0",
      "1984": "231.5",
      "1985": "126.0",
      "1986": "206.0",
      "1987": "140.0",
      "1988": "208.5",
      "1989": "149.5",
      "1990": "218.0",
      "1991": "173.0",
      "1992": "198.5",
      "1993": "144.5",
      "1994": "223.0",
      "1995": "233.0",
      "1996": "197.5",
      "1997": "169.5",
      "1998": "311.0",
      "1999": "143.0",
      "2000": "187.0",
      "2001": "210.5",
      "2002": "385.0",
      "2003": "173.0",
      "2004": "203.0",
      "2005": "166.5",
      "2006": "84.5",
      "2007": "104.5",
      "2008": "116.0",
      "2009": "216.5",
      "2010": "184.0",
      "2011": "168.0",
      "2012": "112.0",
      "2013": "148.5",
      "2014": "129.5",
      "2015": "114.5",
      "2016": "269.0",
      "2017": "161.0",
      "2018": "206.0 )",
      "2019": "150.0"
    },
    "Feb": {
      "1881": "\u3000",
      "1882": "105.0",
      "1883": "138.3",
      "1884": "92.6",
      "1885": "95.3",
      "1886": "146.0",
      "1887": "81.8",
      "1888": "110.9",
      "1889": "98.0",
      "1890": "123.1",
      "1891": "86.7",
      "1892": "138.8",
      "1893": "120.4",
      "1894": "99.3",
      "1895": "97.4",
      "1896": "148.8",
      "1897": "118.2",
      "1898": "124.4",
      "1899": "110.8",
      "1900": "201.6",
      "1901": "201.4",
      "1902": "145.6",
      "1903": "155.0",
      "1904": "104.2",
      "1905": "123.9",
      "1906": "174.3",
      "1907": "171.6",
      "1908": "58.0",
      "1909": "89.8",
      "1910": "100.9",
      "1911": "119.1",
      "1912": "236.8",
      "1913": "110.4",
      "1914": "73.8",
      "1915": "152.0",
      "1916": "132.0",
      "1917": "164.9",
      "1918": "73.6",
      "1919": "111.5",
      "1920": "127.2",
      "1921": "125.9",
      "1922": "146.1",
      "1923": "151.8",
      "1924": "180.2",
      "1925": "160.4",
      "1926": "60.0",
      "1927": "121.6",
      "1928": "96.6",
      "1929": "105.2",
      "1930": "78.8",
      "1931": "95.0",
      "1932": "143.0",
      "1933": "134.6",
      "1934": "154.7",
      "1935": "91.1",
      "1936": "93.9",
      "1937": "180.3",
      "1938": "152.5",
      "1939": "123.3",
      "1940": "158.5",
      "1941": "121.3",
      "1942": "136.3",
      "1943": "227.0",
      "1944": "126.6",
      "1945": "75.2",
      "1946": "99.9",
      "1947": "151.4",
      "1948": "75.7",
      "1949": "159.7",
      "1950": "124.5",
      "1951": "84.5",
      "1952": "158.2",
      "1953": "130.2",
      "1954": "103.2",
      "1955": "100.8",
      "1956": "163.9",
      "1957": "146.2",
      "1958": "97.1",
      "1959": "125.7",
      "1960": "108.0",
      "1961": "191.8",
      "1962": "131.1",
      "1963": "148.2",
      "1964": "114.0",
      "1965": "120.2",
      "1966": "118.8",
      "1967": "133.6",
      "1968": "173.0",
      "1969": "119.5",
      "1970": "80.5",
      "1971": "109.5",
      "1972": "117.5",
      "1973": "108.0",
      "1974": "112.0",
      "1975": "115.0",
      "1976": "180.0",
      "1977": "128.0",
      "1978": "146.0",
      "1979": "162.0",
      "1980": "128.5",
      "1981": "111.0",
      "1982": "61.5",
      "1983": "262.0",
      "1984": "101.0",
      "1985": "79.5",
      "1986": "97.5",
      "1987": "123.0",
      "1988": "149.0",
      "1989": "138.5",
      "1990": "113.0",
      "1991": "194.0",
      "1992": "205.0",
      "1993": "167.5",
      "1994": "105.0",
      "1995": "67.5",
      "1996": "111.5",
      "1997": "92.0",
      "1998": "89.5",
      "1999": "135.5",
      "2000": "130.5",
      "2001": "165.0",
      "2002": "81.0",
      "2003": "47.0",
      "2004": "110.0",
      "2005": "122.5",
      "2006": "92.0",
      "2007": "72.0",
      "2008": "119.5",
      "2009": "124.5",
      "2010": "204.0",
      "2011": "100.0",
      "2012": "179.0",
      "2013": "93.5",
      "2014": "73.5",
      "2015": "92.5",
      "2016": "130.0",
      "2017": "95.0",
      "2018": "108.5",
      "2019": "65.5"
    },
    "Mar": {
      "1881": "\u3000",
      "1882": "115.5",
      "1883": "154.6",
      "1884": "107.7",
      "1885": "102.4",
      "1886": "76.1",
      "1887": "74.6",
      "1888": "100.1",
      "1889": "90.1",
      "1890": "88.6",
      "1891": "108.3",
      "1892": "110.9",
      "1893": "73.9",
      "1894": "98.5",
      "1895": "121.6",
      "1896": "114.1",
      "1897": "113.3",
      "1898": "139.7",
      "1899": "112.2",
      "1900": "106.7",
      "1901": "95.4",
      "1902": "133.0",
      "1903": "134.2",
      "1904": "100.8",
      "1905": "51.1",
      "1906": "108.5",
      "1907": "113.8",
      "1908": "97.7",
      "1909": "129.8",
      "1910": "121.4",
      "1911": "105.8",
      "1912": "153.5",
      "1913": "104.7",
      "1914": "104.1",
      "1915": "156.3",
      "1916": "122.2",
      "1917": "142.0",
      "1918": "67.7",
      "1919": "99.0",
      "1920": "107.4",
      "1921": "207.3",
      "1922": "74.6",
      "1923": "124.4",
      "1924": "76.8",
      "1925": "102.7",
      "1926": "126.3",
      "1927": "121.0",
      "1928": "121.6",
      "1929": "87.9",
      "1930": "105.9",
      "1931": "82.5",
      "1932": "127.6",
      "1933": "164.7",
      "1934": "92.2",
      "1935": "116.0",
      "1936": "83.8",
      "1937": "89.6",
      "1938": "87.6",
      "1939": "124.6",
      "1940": "90.4",
      "1941": "97.5",
      "1942": "79.5",
      "1943": "81.0",
      "1944": "162.6",
      "1945": "160.6",
      "1946": "95.5",
      "1947": "176.8",
      "1948": "98.0",
      "1949": "119.7",
      "1950": "72.8",
      "1951": "89.0",
      "1952": "77.6",
      "1953": "153.4",
      "1954": "154.4",
      "1955": "133.6",
      "1956": "137.0",
      "1957": "91.2",
      "1958": "100.8",
      "1959": "199.2",
      "1960": "133.8",
      "1961": "82.9",
      "1962": "103.9",
      "1963": "101.7",
      "1964": "98.8",
      "1965": "74.8",
      "1966": "117.1",
      "1967": "102.7",
      "1968": "124.5",
      "1969": "137.0",
      "1970": "73.5",
      "1971": "87.5",
      "1972": "175.5",
      "1973": "88.5",
      "1974": "109.5",
      "1975": "84.0",
      "1976": "81.0",
      "1977": "94.0",
      "1978": "73.5",
      "1979": "85.0",
      "1980": "95.5",
      "1981": "73.0",
      "1982": "82.5",
      "1983": "128.0",
      "1984": "116.5",
      "1985": "153.0",
      "1986": "120.5",
      "1987": "121.5",
      "1988": "120.5",
      "1989": "109.5",
      "1990": "74.0",
      "1991": "82.5",
      "1992": "128.0",
      "1993": "133.5",
      "1994": "73.5",
      "1995": "113.5",
      "1996": "148.5",
      "1997": "98.0",
      "1998": "93.0",
      "1999": "105.0",
      "2000": "89.0",
      "2001": "115.5",
      "2002": "135.5",
      "2003": "106.5",
      "2004": "84.0",
      "2005": "141.5",
      "2006": "157.5",
      "2007": "131.5",
      "2008": "52.5",
      "2009": "140.0",
      "2010": "150.5",
      "2011": "103.0",
      "2012": "182.0",
      "2013": "93.5",
      "2014": "151.5",
      "2015": "117.0",
      "2016": "41.5",
      "2017": "69.0",
      "2018": "111.0",
      "2019": "92.0"
    },
    "Apr": {
      "1881": "\u3000",
      "1882": "87.9",
      "1883": "125.1",
      "1884": "99.1",
      "1885": "192.7",
      "1886": "110.5",
      "1887": "81.3",
      "1888": "74.6",
      "1889": "144.4",
      "1890": "242.3",
      "1891": "87.1",
      "1892": "72.8",
      "1893": "61.6",
      "1894": "79.0",
      "1895": "41.9",
      "1896": "124.9",
      "1897": "193.8",
      "1898": "92.6",
      "1899": "67.3",
      "1900": "119.4",
      "1901": "60.6",
      "1902": "134.7",
      "1903": "119.2",
      "1904": "152.7",
      "1905": "137.0",
      "1906": "99.0",
      "1907": "122.3",
      "1908": "108.2",
      "1909": "67.8",
      "1910": "55.2",
      "1911": "115.8",
      "1912": "94.9",
      "1913": "182.0",
      "1914": "103.9",
      "1915": "125.3",
      "1916": "116.8",
      "1917": "62.9",
      "1918": "92.1",
      "1919": "110.7",
      "1920": "78.3",
      "1921": "82.9",
      "1922": "42.1",
      "1923": "107.9",
      "1924": "44.7",
      "1925": "57.5",
      "1926": "125.8",
      "1927": "128.1",
      "1928": "88.9",
      "1929": "95.5",
      "1930": "154.8",
      "1931": "126.5",
      "1932": "122.4",
      "1933": "90.6",
      "1934": "100.7",
      "1935": "104.1",
      "1936": "143.1",
      "1937": "129.6",
      "1938": "111.5",
      "1939": "115.3",
      "1940": "75.9",
      "1941": "110.4",
      "1942": "103.2",
      "1943": "85.8",
      "1944": "143.3",
      "1945": "67.9",
      "1946": "123.6",
      "1947": "76.1",
      "1948": "87.4",
      "1949": "133.4",
      "1950": "81.1",
      "1951": "96.1",
      "1952": "147.1",
      "1953": "110.3",
      "1954": "120.3",
      "1955": "82.2",
      "1956": "113.4",
      "1957": "97.8",
      "1958": "131.3",
      "1959": "87.6",
      "1960": "75.6",
      "1961": "96.2",
      "1962": "75.3",
      "1963": "105.9",
      "1964": "132.2",
      "1965": "58.9",
      "1966": "68.2",
      "1967": "92.3",
      "1968": "82.0",
      "1969": "139.5",
      "1970": "39.0",
      "1971": "83.5",
      "1972": "105.0",
      "1973": "94.5",
      "1974": "69.5",
      "1975": "33.5",
      "1976": "102.5",
      "1977": "96.0",
      "1978": "84.0",
      "1979": "106.5",
      "1980": "140.5",
      "1981": "93.0",
      "1982": "108.0",
      "1983": "116.0",
      "1984": "70.5",
      "1985": "80.5",
      "1986": "95.5",
      "1987": "48.5",
      "1988": "100.0",
      "1989": "128.0",
      "1990": "118.0",
      "1991": "90.0",
      "1992": "126.5",
      "1993": "87.5",
      "1994": "20.5",
      "1995": "114.5",
      "1996": "45.5",
      "1997": "149.5",
      "1998": "131.5",
      "1999": "81.0",
      "2000": "86.5",
      "2001": "33.0",
      "2002": "77.0",
      "2003": "174.0",
      "2004": "111.5",
      "2005": "53.0",
      "2006": "82.0",
      "2007": "83.5",
      "2008": "57.0",
      "2009": "78.0",
      "2010": "110.5",
      "2011": "118.5",
      "2012": "94.0",
      "2013": "142.0",
      "2014": "48.0",
      "2015": "145.0",
      "2016": "120.5",
      "2017": "99.5",
      "2018": "139.5",
      "2019": "16.5 ]"
    },
    "May": {
      "1881": "\u3000",
      "1882": "71.0",
      "1883": "65.1",
      "1884": "101.8",
      "1885": "55.7",
      "1886": "85.8",
      "1887": "63.6",
      "1888": "65.0",
      "1889": "71.0",
      "1890": "72.9",
      "1891": "50.9",
      "1892": "147.6",
      "1893": "161.7",
      "1894": "94.5",
      "1895": "55.9",
      "1896": "45.7",
      "1897": "92.2",
      "1898": "58.6",
      "1899": "82.0",
      "1900": "107.9",
      "1901": "82.1",
      "1902": "108.8",
      "1903": "106.5",
      "1904": "147.4",
      "1905": "82.6",
      "1906": "94.4",
      "1907": "130.6",
      "1908": "104.4",
      "1909": "119.6",
      "1910": "87.6",
      "1911": "72.5",
      "1912": "91.2",
      "1913": "72.3",
      "1914": "102.0",
      "1915": "96.4",
      "1916": "67.9",
      "1917": "45.8",
      "1918": "86.9",
      "1919": "139.9",
      "1920": "98.8",
      "1921": "64.4",
      "1922": "86.6",
      "1923": "148.3",
      "1924": "85.3",
      "1925": "101.9",
      "1926": "35.7",
      "1927": "80.8",
      "1928": "38.7",
      "1929": "89.4",
      "1930": "111.1",
      "1931": "40.6",
      "1932": "68.4",
      "1933": "80.2",
      "1934": "67.6",
      "1935": "84.0",
      "1936": "85.7",
      "1937": "156.7",
      "1938": "125.6",
      "1939": "84.0",
      "1940": "85.2",
      "1941": "114.6",
      "1942": "88.1",
      "1943": "65.0",
      "1944": "123.0",
      "1945": "79.1",
      "1946": "94.4",
      "1947": "116.7",
      "1948": "58.9",
      "1949": "104.9",
      "1950": "105.5",
      "1951": "54.8",
      "1952": "81.8",
      "1953": "58.5",
      "1954": "143.5",
      "1955": "116.6",
      "1956": "135.8",
      "1957": "123.4",
      "1958": "57.4",
      "1959": "91.7",
      "1960": "77.0",
      "1961": "54.1",
      "1962": "105.2",
      "1963": "205.5",
      "1964": "62.3",
      "1965": "128.1",
      "1966": "118.1",
      "1967": "52.6",
      "1968": "75.5",
      "1969": "80.5",
      "1970": "35.0",
      "1971": "77.0",
      "1972": "137.5",
      "1973": "53.0",
      "1974": "97.5",
      "1975": "99.5",
      "1976": "58.0",
      "1977": "108.0",
      "1978": "53.0",
      "1979": "67.0",
      "1980": "128.0",
      "1981": "160.5",
      "1982": "110.0",
      "1983": "84.5",
      "1984": "74.0",
      "1985": "215.0",
      "1986": "74.0",
      "1987": "145.0",
      "1988": "146.0",
      "1989": "76.0",
      "1990": "64.0",
      "1991": "91.5",
      "1992": "111.0",
      "1993": "145.0",
      "1994": "36.5",
      "1995": "47.5",
      "1996": "130.0",
      "1997": "188.0",
      "1998": "197.0",
      "1999": "63.5",
      "2000": "62.0",
      "2001": "40.0",
      "2002": "103.0",
      "2003": "66.5",
      "2004": "192.5",
      "2005": "49.5",
      "2006": "132.0",
      "2007": "56.0",
      "2008": "74.0",
      "2009": "50.5",
      "2010": "136.5",
      "2011": "96.5",
      "2012": "130.0",
      "2013": "50.0",
      "2014": "90.0",
      "2015": "63.0",
      "2016": "90.0",
      "2017": "56.0",
      "2018": "139.0",
      "2019": "\u3000"
    },
    "Jun": {
      "1881": "\u3000",
      "1882": "76.5",
      "1883": "61.2",
      "1884": "81.8",
      "1885": "234.2",
      "1886": "129.6",
      "1887": "70.6",
      "1888": "100.8",
      "1889": "215.9",
      "1890": "188.5",
      "1891": "96.6",
      "1892": "181.5",
      "1893": "70.4",
      "1894": "150.3",
      "1895": "81.8",
      "1896": "161.9",
      "1897": "53.6",
      "1898": "261.2",
      "1899": "115.9",
      "1900": "29.6",
      "1901": "145.5",
      "1902": "49.5",
      "1903": "81.6",
      "1904": "108.0",
      "1905": "192.8",
      "1906": "134.1",
      "1907": "154.1",
      "1908": "165.2",
      "1909": "160.1",
      "1910": "223.4",
      "1911": "210.8",
      "1912": "58.0",
      "1913": "103.8",
      "1914": "104.4",
      "1915": "148.9",
      "1916": "212.9",
      "1917": "162.8",
      "1918": "60.0",
      "1919": "103.1",
      "1920": "136.7",
      "1921": "92.4",
      "1922": "56.2",
      "1923": "111.5",
      "1924": "106.6",
      "1925": "45.3",
      "1926": "52.9",
      "1927": "18.1",
      "1928": "124.5",
      "1929": "28.0",
      "1930": "107.6",
      "1931": "83.4",
      "1932": "117.0",
      "1933": "70.3",
      "1934": "115.3",
      "1935": "81.7",
      "1936": "77.9",
      "1937": "65.9",
      "1938": "158.3",
      "1939": "66.3",
      "1940": "65.9",
      "1941": "143.9",
      "1942": "97.6",
      "1943": "63.1",
      "1944": "62.3",
      "1945": "146.5",
      "1946": "218.3",
      "1947": "252.5",
      "1948": "53.5",
      "1949": "209.7",
      "1950": "185.7",
      "1951": "77.1",
      "1952": "160.4",
      "1953": "108.9",
      "1954": "121.2",
      "1955": "105.0",
      "1956": "158.5",
      "1957": "77.9",
      "1958": "86.5",
      "1959": "86.6",
      "1960": "114.7",
      "1961": "190.6",
      "1962": "154.4",
      "1963": "114.0",
      "1964": "98.5",
      "1965": "159.8",
      "1966": "109.9",
      "1967": "88.7",
      "1968": "43.0",
      "1969": "57.0",
      "1970": "61.0",
      "1971": "196.5",
      "1972": "113.5",
      "1973": "79.5",
      "1974": "58.0",
      "1975": "85.0",
      "1976": "170.5",
      "1977": "61.5",
      "1978": "378.0",
      "1979": "93.5",
      "1980": "119.5",
      "1981": "250.0",
      "1982": "71.0",
      "1983": "63.5",
      "1984": "89.5",
      "1985": "73.5",
      "1986": "137.5",
      "1987": "52.0",
      "1988": "100.0",
      "1989": "89.5",
      "1990": "158.0",
      "1991": "135.0",
      "1992": "97.5",
      "1993": "151.5",
      "1994": "62.0",
      "1995": "52.0",
      "1996": "185.0",
      "1997": "293.0",
      "1998": "88.0",
      "1999": "215.5",
      "2000": "130.0",
      "2001": "279.5",
      "2002": "70.0",
      "2003": "123.0",
      "2004": "132.5",
      "2005": "169.5",
      "2006": "70.0",
      "2007": "229.0",
      "2008": "54.0",
      "2009": "68.0",
      "2010": "148.5",
      "2011": "191.0",
      "2012": "37.5",
      "2013": "93.5",
      "2014": "63.0",
      "2015": "50.0",
      "2016": "73.5",
      "2017": "48.0",
      "2018": "66.5",
      "2019": "\u3000"
    },
    "Jul": {
      "1881": "180.2",
      "1882": "123.0",
      "1883": "36.4",
      "1884": "203.5",
      "1885": "157.4",
      "1886": "18.7",
      "1887": "183.6",
      "1888": "92.6",
      "1889": "223.1",
      "1890": "120.7",
      "1891": "302.3",
      "1892": "164.5",
      "1893": "58.9",
      "1894": "58.0",
      "1895": "126.5",
      "1896": "229.3",
      "1897": "235.4",
      "1898": "213.4",
      "1899": "126.3",
      "1900": "182.4",
      "1901": "255.5",
      "1902": "184.5",
      "1903": "229.0",
      "1904": "226.0",
      "1905": "164.8",
      "1906": "70.4",
      "1907": "47.9",
      "1908": "99.3",
      "1909": "72.1",
      "1910": "237.9",
      "1911": "262.1",
      "1912": "320.1",
      "1913": "138.4",
      "1914": "313.8",
      "1915": "29.0",
      "1916": "164.1",
      "1917": "119.1",
      "1918": "141.2",
      "1919": "62.8",
      "1920": "112.9",
      "1921": "159.4",
      "1922": "205.0",
      "1923": "113.5",
      "1924": "150.8",
      "1925": "104.1",
      "1926": "257.7",
      "1927": "274.4",
      "1928": "44.8",
      "1929": "44.4",
      "1930": "271.8",
      "1931": "167.8",
      "1932": "208.5",
      "1933": "191.9",
      "1934": "332.6",
      "1935": "148.2",
      "1936": "117.5",
      "1937": "187.5",
      "1938": "136.3",
      "1939": "117.8",
      "1940": "77.9",
      "1941": "186.6",
      "1942": "104.5",
      "1943": "27.7",
      "1944": "271.5",
      "1945": "219.4",
      "1946": "189.9",
      "1947": "411.3",
      "1948": "96.1",
      "1949": "22.4",
      "1950": "46.4",
      "1951": "135.1",
      "1952": "241.2",
      "1953": "276.3",
      "1954": "156.4",
      "1955": "137.9",
      "1956": "202.2",
      "1957": "214.7",
      "1958": "511.8",
      "1959": "227.3",
      "1960": "180.3",
      "1961": "154.9",
      "1962": "88.8",
      "1963": "129.3",
      "1964": "351.7",
      "1965": "307.1",
      "1966": "412.3",
      "1967": "90.6",
      "1968": "38.5",
      "1969": "178.0",
      "1970": "177.5",
      "1971": "313.5",
      "1972": "168.0",
      "1973": "14.5",
      "1974": "220.0",
      "1975": "149.0",
      "1976": "109.0",
      "1977": "90.0",
      "1978": "34.5",
      "1979": "271.0",
      "1980": "270.5",
      "1981": "102.0",
      "1982": "152.5",
      "1983": "271.0",
      "1984": "307.0",
      "1985": "305.0",
      "1986": "150.5",
      "1987": "236.0",
      "1988": "182.0",
      "1989": "105.0",
      "1990": "75.5",
      "1991": "315.5",
      "1992": "114.5",
      "1993": "210.0",
      "1994": "63.0",
      "1995": "358.0",
      "1996": "80.0",
      "1997": "257.5",
      "1998": "112.0",
      "1999": "133.5",
      "2000": "175.5",
      "2001": "28.0",
      "2002": "386.5",
      "2003": "248.0",
      "2004": "222.5",
      "2005": "103.5",
      "2006": "466.0",
      "2007": "135.0",
      "2008": "101.5",
      "2009": "255.0",
      "2010": "109.5",
      "2011": "332.0",
      "2012": "163.5",
      "2013": "413.0",
      "2014": "314.5",
      "2015": "167.0",
      "2016": "194.5",
      "2017": "443.0",
      "2018": "42.0",
      "2019": "\u3000"
    },
    "Aug": {
      "1881": "21.8",
      "1882": "110.8",
      "1883": "76.2",
      "1884": "95.3",
      "1885": "237.4",
      "1886": "111.9",
      "1887": "86.6",
      "1888": "158.2",
      "1889": "54.3",
      "1890": "71.4",
      "1891": "157.7",
      "1892": "72.8",
      "1893": "146.7",
      "1894": "155.4",
      "1895": "69.9",
      "1896": "94.8",
      "1897": "338.3",
      "1898": "151.6",
      "1899": "196.9",
      "1900": "101.1",
      "1901": "88.1",
      "1902": "112.0",
      "1903": "59.6",
      "1904": "37.6",
      "1905": "331.2",
      "1906": "135.7",
      "1907": "182.2",
      "1908": "86.0",
      "1909": "34.1",
      "1910": "238.9",
      "1911": "183.2",
      "1912": "44.6",
      "1913": "158.9",
      "1914": "135.0",
      "1915": "118.1",
      "1916": "57.7",
      "1917": "105.1",
      "1918": "116.1",
      "1919": "106.9",
      "1920": "86.6",
      "1921": "114.4",
      "1922": "80.6",
      "1923": "5.0",
      "1924": "94.5",
      "1925": "100.9",
      "1926": "180.8",
      "1927": "134.8",
      "1928": "10.2",
      "1929": "149.5",
      "1930": "69.6",
      "1931": "89.9",
      "1932": "112.4",
      "1933": "107.3",
      "1934": "236.3",
      "1935": "157.7",
      "1936": "235.6",
      "1937": "110.7",
      "1938": "16.9",
      "1939": "75.2",
      "1940": "77.4",
      "1941": "43.0",
      "1942": "123.6",
      "1943": "92.0",
      "1944": "63.3",
      "1945": "42.1",
      "1946": "35.7",
      "1947": "86.8",
      "1948": "47.0",
      "1949": "34.7",
      "1950": "100.5",
      "1951": "49.0",
      "1952": "137.5",
      "1953": "343.4",
      "1954": "42.5",
      "1955": "106.5",
      "1956": "95.7",
      "1957": "129.0",
      "1958": "244.0",
      "1959": "201.9",
      "1960": "111.5",
      "1961": "250.6",
      "1962": "46.9",
      "1963": "191.7",
      "1964": "142.2",
      "1965": "39.5",
      "1966": "51.7",
      "1967": "352.0",
      "1968": "266.0",
      "1969": "146.5",
      "1970": "50.5",
      "1971": "121.5",
      "1972": "218.5",
      "1973": "39.5",
      "1974": "102.5",
      "1975": "87.0",
      "1976": "430.5",
      "1977": "150.0",
      "1978": "111.5",
      "1979": "130.0",
      "1980": "250.0",
      "1981": "213.0",
      "1982": "38.5",
      "1983": "89.5",
      "1984": "17.5",
      "1985": "3.5",
      "1986": "67.5",
      "1987": "166.0",
      "1988": "40.0",
      "1989": "116.5",
      "1990": "85.0",
      "1991": "156.5",
      "1992": "88.0",
      "1993": "181.5",
      "1994": "65.0",
      "1995": "303.5",
      "1996": "84.0",
      "1997": "129.5",
      "1998": "616.0",
      "1999": "167.0",
      "2000": "11.5",
      "2001": "135.5",
      "2002": "128.0",
      "2003": "182.5",
      "2004": "178.0",
      "2005": "193.0",
      "2006": "78.0",
      "2007": "286.5",
      "2008": "201.0",
      "2009": "142.0",
      "2010": "54.5",
      "2011": "51.0",
      "2012": "28.0",
      "2013": "264.5",
      "2014": "163.5",
      "2015": "114.5",
      "2016": "85.0",
      "2017": "258.0",
      "2018": "278.0",
      "2019": "\u3000"
    },
    "Sep": {
      "1881": "227.6",
      "1882": "25.3",
      "1883": "224.8",
      "1884": "267.7",
      "1885": "107.9",
      "1886": "73.3",
      "1887": "170.1",
      "1888": "153.5",
      "1889": "202.8",
      "1890": "98.0",
      "1891": "270.6",
      "1892": "209.0",
      "1893": "101.7",
      "1894": "121.2",
      "1895": "27.7",
      "1896": "133.1",
      "1897": "377.5",
      "1898": "137.2",
      "1899": "224.1",
      "1900": "262.7",
      "1901": "179.1",
      "1902": "241.4",
      "1903": "174.7",
      "1904": "215.9",
      "1905": "298.4",
      "1906": "181.2",
      "1907": "134.1",
      "1908": "95.9",
      "1909": "315.9",
      "1910": "266.7",
      "1911": "293.8",
      "1912": "115.1",
      "1913": "104.1",
      "1914": "73.4",
      "1915": "236.5",
      "1916": "372.6",
      "1917": "370.6",
      "1918": "137.6",
      "1919": "158.9",
      "1920": "200.2",
      "1921": "194.6",
      "1922": "213.1",
      "1923": "197.1",
      "1924": "127.8",
      "1925": "119.1",
      "1926": "226.4",
      "1927": "210.7",
      "1928": "46.8",
      "1929": "213.3",
      "1930": "139.9",
      "1931": "119.1",
      "1932": "104.0",
      "1933": "137.2",
      "1934": "131.7",
      "1935": "140.8",
      "1936": "156.5",
      "1937": "78.2",
      "1938": "112.1",
      "1939": "305.0",
      "1940": "98.6",
      "1941": "148.3",
      "1942": "221.7",
      "1943": "258.0",
      "1944": "139.2",
      "1945": "231.6",
      "1946": "160.1",
      "1947": "204.4",
      "1948": "217.1",
      "1949": "158.4",
      "1950": "176.7",
      "1951": "113.8",
      "1952": "183.4",
      "1953": "138.6",
      "1954": "95.8",
      "1955": "154.0",
      "1956": "172.6",
      "1957": "121.8",
      "1958": "337.3",
      "1959": "119.5",
      "1960": "179.6",
      "1961": "156.0",
      "1962": "89.9",
      "1963": "171.3",
      "1964": "294.5",
      "1965": "138.8",
      "1966": "210.1",
      "1967": "123.4",
      "1968": "32.5",
      "1969": "166.5",
      "1970": "186.0",
      "1971": "211.5",
      "1972": "145.5",
      "1973": "134.5",
      "1974": "170.5",
      "1975": "69.5",
      "1976": "190.0",
      "1977": "126.0",
      "1978": "114.5",
      "1979": "191.5",
      "1980": "62.0",
      "1981": "119.0",
      "1982": "143.0",
      "1983": "172.5",
      "1984": "217.5",
      "1985": "313.0",
      "1986": "102.5",
      "1987": "60.0",
      "1988": "144.5",
      "1989": "331.5",
      "1990": "132.5",
      "1991": "112.5",
      "1992": "25.5",
      "1993": "122.0",
      "1994": "293.0",
      "1995": "185.0",
      "1996": "131.0",
      "1997": "205.0",
      "1998": "138.5",
      "1999": "242.5",
      "2000": "284.0",
      "2001": "192.5",
      "2002": "87.0",
      "2003": "73.5",
      "2004": "109.0",
      "2005": "76.5",
      "2006": "92.0",
      "2007": "54.0",
      "2008": "93.5",
      "2009": "66.0",
      "2010": "334.5",
      "2011": "250.0",
      "2012": "224.0",
      "2013": "165.0",
      "2014": "103.0",
      "2015": "145.5",
      "2016": "127.0",
      "2017": "95.5",
      "2018": "248.5",
      "2019": "\u3000"
    },
    "Oct": {
      "1881": "111.2",
      "1882": "125.8",
      "1883": "199.3",
      "1884": "171.6",
      "1885": "187.6",
      "1886": "172.8",
      "1887": "78.8",
      "1888": "258.9",
      "1889": "117.5",
      "1890": "203.7",
      "1891": "77.8",
      "1892": "74.0",
      "1893": "189.9",
      "1894": "108.9",
      "1895": "127.7",
      "1896": "181.4",
      "1897": "153.2",
      "1898": "48.0",
      "1899": "244.9",
      "1900": "230.8",
      "1901": "152.3",
      "1902": "94.1",
      "1903": "155.5",
      "1904": "167.3",
      "1905": "183.8",
      "1906": "138.8",
      "1907": "142.1",
      "1908": "136.2",
      "1909": "124.6",
      "1910": "93.7",
      "1911": "212.3",
      "1912": "116.0",
      "1913": "210.3",
      "1914": "222.6",
      "1915": "200.8",
      "1916": "146.6",
      "1917": "221.8",
      "1918": "166.8",
      "1919": "142.1",
      "1920": "133.9",
      "1921": "145.4",
      "1922": "158.2",
      "1923": "310.3",
      "1924": "248.1",
      "1925": "138.2",
      "1926": "263.1",
      "1927": "163.7",
      "1928": "194.3",
      "1929": "132.8",
      "1930": "100.2",
      "1931": "215.0",
      "1932": "151.0",
      "1933": "246.4",
      "1934": "148.2",
      "1935": "129.3",
      "1936": "119.5",
      "1937": "110.1",
      "1938": "192.7",
      "1939": "123.6",
      "1940": "88.1",
      "1941": "100.3",
      "1942": "189.9",
      "1943": "281.4",
      "1944": "82.5",
      "1945": "240.5",
      "1946": "198.1",
      "1947": "176.8",
      "1948": "266.3",
      "1949": "150.0",
      "1950": "251.2",
      "1951": "95.9",
      "1952": "138.1",
      "1953": "97.0",
      "1954": "126.2",
      "1955": "241.8",
      "1956": "84.0",
      "1957": "130.8",
      "1958": "206.9",
      "1959": "159.0",
      "1960": "102.0",
      "1961": "151.3",
      "1962": "205.7",
      "1963": "158.6",
      "1964": "178.8",
      "1965": "138.1",
      "1966": "263.0",
      "1967": "118.6",
      "1968": "183.0",
      "1969": "161.5",
      "1970": "161.0",
      "1971": "103.5",
      "1972": "127.5",
      "1973": "147.0",
      "1974": "151.5",
      "1975": "285.0",
      "1976": "109.5",
      "1977": "15.5",
      "1978": "99.0",
      "1979": "168.0",
      "1980": "233.5",
      "1981": "266.0",
      "1982": "74.0",
      "1983": "136.0",
      "1984": "118.5",
      "1985": "192.5",
      "1986": "219.5",
      "1987": "92.5",
      "1988": "172.0",
      "1989": "151.0",
      "1990": "178.5",
      "1991": "190.5",
      "1992": "148.0",
      "1993": "128.5",
      "1994": "126.0",
      "1995": "70.5",
      "1996": "114.0",
      "1997": "143.5",
      "1998": "216.5",
      "1999": "151.0",
      "2000": "137.0",
      "2001": "84.0",
      "2002": "254.0",
      "2003": "153.5",
      "2004": "237.5",
      "2005": "212.5",
      "2006": "181.5",
      "2007": "136.0",
      "2008": "217.0",
      "2009": "172.5",
      "2010": "134.0",
      "2011": "117.0",
      "2012": "193.0",
      "2013": "176.0",
      "2014": "229.0",
      "2015": "106.0",
      "2016": "99.0",
      "2017": "150.5",
      "2018": "154.0",
      "2019": "\u3000"
    },
    "Nov": {
      "1881": "275.8",
      "1882": "152.4",
      "1883": "255.4",
      "1884": "248.4",
      "1885": "278.6",
      "1886": "249.8",
      "1887": "193.5",
      "1888": "173.9",
      "1889": "225.1",
      "1890": "130.0",
      "1891": "156.8",
      "1892": "164.6",
      "1893": "298.5",
      "1894": "129.9",
      "1895": "153.7",
      "1896": "128.5",
      "1897": "116.2",
      "1898": "144.1",
      "1899": "148.1",
      "1900": "205.2",
      "1901": "210.0",
      "1902": "137.6",
      "1903": "234.5",
      "1904": "285.5",
      "1905": "158.5",
      "1906": "159.4",
      "1907": "176.2",
      "1908": "257.3",
      "1909": "194.1",
      "1910": "131.9",
      "1911": "243.0",
      "1912": "167.9",
      "1913": "210.2",
      "1914": "199.2",
      "1915": "129.8",
      "1916": "159.7",
      "1917": "298.4",
      "1918": "246.0",
      "1919": "151.8",
      "1920": "143.4",
      "1921": "351.1",
      "1922": "329.0",
      "1923": "254.1",
      "1924": "314.3",
      "1925": "130.4",
      "1926": "117.5",
      "1927": "221.5",
      "1928": "188.6",
      "1929": "197.4",
      "1930": "308.0",
      "1931": "128.0",
      "1932": "189.3",
      "1933": "126.1",
      "1934": "211.4",
      "1935": "141.5",
      "1936": "132.3",
      "1937": "244.2",
      "1938": "222.4",
      "1939": "238.2",
      "1940": "151.6",
      "1941": "87.6",
      "1942": "217.4",
      "1943": "246.5",
      "1944": "120.9",
      "1945": "195.8",
      "1946": "103.4",
      "1947": "115.1",
      "1948": "156.1",
      "1949": "147.9",
      "1950": "152.5",
      "1951": "337.3",
      "1952": "110.3",
      "1953": "222.5",
      "1954": "123.9",
      "1955": "176.7",
      "1956": "232.2",
      "1957": "101.0",
      "1958": "214.6",
      "1959": "150.5",
      "1960": "193.5",
      "1961": "221.1",
      "1962": "199.7",
      "1963": "161.5",
      "1964": "190.5",
      "1965": "181.2",
      "1966": "195.7",
      "1967": "137.3",
      "1968": "186.5",
      "1969": "176.0",
      "1970": "268.5",
      "1971": "187.0",
      "1972": "283.5",
      "1973": "302.0",
      "1974": "126.5",
      "1975": "129.5",
      "1976": "156.0",
      "1977": "272.0",
      "1978": "135.5",
      "1979": "216.5",
      "1980": "84.5",
      "1981": "268.5",
      "1982": "170.0",
      "1983": "205.5",
      "1984": "126.0",
      "1985": "370.0",
      "1986": "97.5",
      "1987": "123.0",
      "1988": "346.0",
      "1989": "191.5",
      "1990": "200.5",
      "1991": "245.5",
      "1992": "123.5",
      "1993": "172.5",
      "1994": "167.5",
      "1995": "230.5",
      "1996": "219.0",
      "1997": "161.5",
      "1998": "243.5",
      "1999": "267.5",
      "2000": "195.0",
      "2001": "208.5",
      "2002": "405.0",
      "2003": "164.0",
      "2004": "144.0",
      "2005": "231.0",
      "2006": "253.0",
      "2007": "149.5",
      "2008": "280.0",
      "2009": "169.0",
      "2010": "196.0",
      "2011": "137.0",
      "2012": "283.5",
      "2013": "416.0",
      "2014": "174.5",
      "2015": "187.0",
      "2016": "89.5",
      "2017": "231.5",
      "2018": "97.0",
      "2019": "\u3000"
    },
    "Dec": {
      "1881": "203.0",
      "1882": "227.0",
      "1883": "330.6",
      "1884": "154.6",
      "1885": "164.9",
      "1886": "246.7",
      "1887": "257.5",
      "1888": "242.8",
      "1889": "241.9",
      "1890": "237.5",
      "1891": "110.5",
      "1892": "190.8",
      "1893": "218.9",
      "1894": "171.6",
      "1895": "316.7",
      "1896": "305.7",
      "1897": "318.2",
      "1898": "286.7",
      "1899": "215.1",
      "1900": "199.4",
      "1901": "242.8",
      "1902": "158.8",
      "1903": "237.8",
      "1904": "187.2",
      "1905": "274.4",
      "1906": "244.4",
      "1907": "181.1",
      "1908": "154.0",
      "1909": "235.9",
      "1910": "335.9",
      "1911": "220.1",
      "1912": "223.3",
      "1913": "344.8",
      "1914": "304.3",
      "1915": "155.2",
      "1916": "198.9",
      "1917": "285.8",
      "1918": "191.2",
      "1919": "266.4",
      "1920": "234.9",
      "1921": "131.6",
      "1922": "200.0",
      "1923": "210.2",
      "1924": "206.0",
      "1925": "290.3",
      "1926": "199.9",
      "1927": "142.3",
      "1928": "180.7",
      "1929": "165.9",
      "1930": "153.7",
      "1931": "256.7",
      "1932": "169.6",
      "1933": "243.5",
      "1934": "129.7",
      "1935": "349.3",
      "1936": "191.3",
      "1937": "282.6",
      "1938": "262.1",
      "1939": "211.1",
      "1940": "245.8",
      "1941": "216.9",
      "1942": "286.4",
      "1943": "186.8",
      "1944": "342.7",
      "1945": "352.2",
      "1946": "328.5",
      "1947": "231.1",
      "1948": "226.9",
      "1949": "173.9",
      "1950": "281.8",
      "1951": "316.7",
      "1952": "366.5",
      "1953": "182.3",
      "1954": "233.7",
      "1955": "162.0",
      "1956": "249.3",
      "1957": "274.7",
      "1958": "186.9",
      "1959": "280.8",
      "1960": "397.1",
      "1961": "242.0",
      "1962": "289.6",
      "1963": "179.1",
      "1964": "157.9",
      "1965": "290.4",
      "1966": "243.7",
      "1967": "334.1",
      "1968": "227.5",
      "1969": "330.0",
      "1970": "180.0",
      "1971": "242.0",
      "1972": "182.0",
      "1973": "334.5",
      "1974": "97.5",
      "1975": "184.0",
      "1976": "198.5",
      "1977": "247.5",
      "1978": "123.0",
      "1979": "193.5",
      "1980": "287.0",
      "1981": "127.5",
      "1982": "293.5",
      "1983": "120.5",
      "1984": "263.0",
      "1985": "316.0",
      "1986": "110.5",
      "1987": "195.5",
      "1988": "177.5",
      "1989": "233.5",
      "1990": "179.0",
      "1991": "132.5",
      "1992": "188.0",
      "1993": "187.0",
      "1994": "210.5 )",
      "1995": "302.5",
      "1996": "253.5",
      "1997": "188.5",
      "1998": "160.5",
      "1999": "258.5",
      "2000": "153.0",
      "2001": "216.0",
      "2002": "171.0",
      "2003": "176.5",
      "2004": "193.0",
      "2005": "294.0",
      "2006": "326.0",
      "2007": "311.0",
      "2008": "164.0",
      "2009": "310.5",
      "2010": "309.5",
      "2011": "194.0",
      "2012": "183.5",
      "2013": "271.5",
      "2014": "444.0",
      "2015": "165.5",
      "2016": "179.5",
      "2017": "329.5",
      "2018": "205.5",
      "2019": "\u3000"
    },
    "Annual": {
      "1881": "1019.6 ]",
      "1882": "1331.2",
      "1883": "1790.8",
      "1884": "1825.4",
      "1885": "1931.2",
      "1886": "1580.1",
      "1887": "1467.9",
      "1888": "1681.3",
      "1889": "1889.3",
      "1890": "1784.0",
      "1891": "1877.7",
      "1892": "1809.9",
      "1893": "1717.9",
      "1894": "1418.0",
      "1895": "1586.7",
      "1896": "1854.1",
      "1897": "2257.8",
      "1898": "1777.6",
      "1899": "1853.0",
      "1900": "1953.3",
      "1901": "1860.4",
      "1902": "1693.3",
      "1903": "1859.0",
      "1904": "1986.5",
      "1905": "2133.5",
      "1906": "1713.3",
      "1907": "1741.7",
      "1908": "1613.1",
      "1909": "1691.2",
      "1910": "2037.9",
      "1911": "2226.6",
      "1912": "1813.6",
      "1913": "1912.9",
      "1914": "1886.3",
      "1915": "1724.2",
      "1916": "1921.3",
      "1917": "2316.4",
      "1918": "1528.2",
      "1919": "1568.7",
      "1920": "1632.7",
      "1921": "1879.4",
      "1922": "1710.4",
      "1923": "1954.1",
      "1924": "1863.4",
      "1925": "1537.5",
      "1926": "1908.5",
      "1927": "1743.1",
      "1928": "1273.1",
      "1929": "1430.3",
      "1930": "1762.6",
      "1931": "1558.3",
      "1932": "1640.7",
      "1933": "1828.7",
      "1934": "1902.0",
      "1935": "1700.8",
      "1936": "1636.1",
      "1937": "1847.0",
      "1938": "1775.8",
      "1939": "1813.9",
      "1940": "1484.0",
      "1941": "1643.5",
      "1942": "1909.4",
      "1943": "1872.4",
      "1944": "1724.2",
      "1945": "2065.9",
      "1946": "1756.6",
      "1947": "2199.2",
      "1948": "1521.2",
      "1949": "1589.1",
      "1950": "1769.4",
      "1951": "1592.4",
      "1952": "2043.4",
      "1953": "1990.4",
      "1954": "1563.4",
      "1955": "1768.6",
      "1956": "1960.8",
      "1957": "1629.1",
      "1958": "2351.2",
      "1959": "1994.3",
      "1960": "1881.0",
      "1961": "2097.1",
      "1962": "1740.0",
      "1963": "2026.5",
      "1964": "1946.6",
      "1965": "1886.3",
      "1966": "2014.2",
      "1967": "1820.5",
      "1968": "1650.5",
      "1969": "1988.0",
      "1970": "1501.0",
      "1971": "1881.0",
      "1972": "1904.5",
      "1973": "1554.0",
      "1974": "1459.5",
      "1975": "1486.5",
      "1976": "1979.0",
      "1977": "1540.0",
      "1978": "1558.0",
      "1979": "1836.0",
      "1980": "2024.5",
      "1981": "1916.0",
      "1982": "1464.5",
      "1983": "1833.0",
      "1984": "1732.5",
      "1985": "2227.5",
      "1986": "1479.0",
      "1987": "1503.0",
      "1988": "1886.0",
      "1989": "1820.0",
      "1990": "1596.0",
      "1991": "1919.0",
      "1992": "1554.0",
      "1993": "1831.0",
      "1994": "1445.5",
      "1995": "2078.0",
      "1996": "1699.5",
      "1997": "2075.5",
      "1998": "2397.0",
      "1999": "1963.5",
      "2000": "1641.0",
      "2001": "1708.0",
      "2002": "2283.0",
      "2003": "1688.0",
      "2004": "1917.5",
      "2005": "1813.0",
      "2006": "2014.5",
      "2007": "1748.5",
      "2008": "1530.0",
      "2009": "1792.5",
      "2010": "2072.0",
      "2011": "1858.0",
      "2012": "1810.0",
      "2013": "2327.0",
      "2014": "1984.0",
      "2015": "1467.5",
      "2016": "1499.0",
      "2017": "2036.5",
      "2018": "1795.5",
      "2019": "324.0 ]"
    }
  }
}